Workbook

Sheet Özet
A1: Büyü / talent / glyph çevirisi düzeltme raporu
A2: Kapsam: Spells_TR.lua (1.170 şablon), Talents_Tmpl_TR.lua (851), Glyphs_TR.lua (345).
A3: Talents_TR.lua (per-rank) düzeltilmiş şablonlardan yeniden üretildi: 732 kayıt değişti.
A4: 35 per-rank kayıt eski hâlinde bırakıldı: şablona sabit yazılan sayı eki (%6'sı) o rank için bozuluyordu.
A5: Terim kararları: Dodge=kaçınma, Strength/Agility/Stamina/Intellect/Spirit/Resilience İngilizce,
A6: Arcane=Arkan, Stun=sersemletme, Daze=afallatma, caster=büyüyü yapan, hitap=sen.
A8: Kategori | B8: Yüksek | C8: Orta | D8: Düşük | E8: Toplam
A9: Mekanik / anlam hatası | B9: =COUNTIFS('Değişiklikler'!$C:$C,$A9,'Değişiklikler'!$D:$D,"Yüksek") | C9: =COUNTIFS('Değişiklikler'!$C:$C,$A9,'Değişiklikler'!$D:$D,"Orta") | D9: =COUNTIFS('Değişiklikler'!$C:$C,$A9,'Değişiklikler'!$D:$D,"Düşük") | E9: =SUM(B9:D9)
A10: Yer tutucu yeri yanlış | B10: =COUNTIFS('Değişiklikler'!$C:$C,$A10,'Değişiklikler'!$D:$D,"Yüksek") | C10: =COUNTIFS('Değişiklikler'!$C:$C,$A10,'Değişiklikler'!$D:$D,"Orta") | D10: =COUNTIFS('Değişiklikler'!$C:$C,$A10,'Değişiklikler'!$D:$D,"Düşük") | E10: =SUM(B10:D10)
A11: Terim tutarlılığı | B11: =COUNTIFS('Değişiklikler'!$C:$C,$A11,'Değişiklikler'!$D:$D,"Yüksek") | C11: =COUNTIFS('Değişiklikler'!$C:$C,$A11,'Değişiklikler'!$D:$D,"Orta") | D11: =COUNTIFS('Değişiklikler'!$C:$C,$A11,'Değişiklikler'!$D:$D,"Düşük") | E11: =SUM(B11:D11)
A12: Sen/siz | B12: =COUNTIFS('Değişiklikler'!$C:$C,$A12,'Değişiklikler'!$D:$D,"Yüksek") | C12: =COUNTIFS('Değişiklikler'!$C:$C,$A12,'Değişiklikler'!$D:$D,"Orta") | D12: =COUNTIFS('Değişiklikler'!$C:$C,$A12,'Değişiklikler'!$D:$D,"Düşük") | E12: =SUM(B12:D12)
A13: Ad / sınıf / okul | B13: =COUNTIFS('Değişiklikler'!$C:$C,$A13,'Değişiklikler'!$D:$D,"Yüksek") | C13: =COUNTIFS('Değişiklikler'!$C:$C,$A13,'Değişiklikler'!$D:$D,"Orta") | D13: =COUNTIFS('Değişiklikler'!$C:$C,$A13,'Değişiklikler'!$D:$D,"Düşük") | E13: =SUM(B13:D13)
A14: Okunurluk / yazım | B14: =COUNTIFS('Değişiklikler'!$C:$C,$A14,'Değişiklikler'!$D:$D,"Yüksek") | C14: =COUNTIFS('Değişiklikler'!$C:$C,$A14,'Değişiklikler'!$D:$D,"Orta") | D14: =COUNTIFS('Değişiklikler'!$C:$C,$A14,'Değişiklikler'!$D:$D,"Düşük") | E14: =SUM(B14:D14)
A15: Toplam | B15: =SUM(B9:B14) | C15: =SUM(C9:C14) | D15: =SUM(D9:D14) | E15: =SUM(E9:E14)

Sheet Değişiklikler
A1: Dosya | B1: Satır (1 tabanlı) | C1: Kategori | D1: Önem | E1: İngilizce şablon | F1: Önceki Türkçe | G1: Yeni Türkçe | H1: Gerekçe
A2: Glyphs_TR.lua | B2: 12 | C2: Mekanik / anlam hatası | D2: Yüksek | E2: Allows Pain Suppression to be cast while stunned. | F2: Pain Suppression'ın sersemletilmişken büyü yapılmasına izin verir. | G2: Pain Suppression'ın sersemletilmişken kullanılabilmesini sağlar. | H2: Pain Suppression: sersemletilmişken kullanılabilmesini sağlar
A3: Glyphs_TR.lua | B3: 29 | C3: Mekanik / anlam hatası | D3: Yüksek | E3: If your Guardian Spirit lasts its entire duration without being triggered, the cooldown is reset to {1} min. | F3: Guardian Spirit'iniz tetiklenmeden tüm süresince devam ederse, bekleme süresi {1} dk'ya sıfırlanır. | G3: Guardian Spirit'in tetiklenmeden tüm süresince devam ederse, bekleme süresi {1} dk'ya düşürülür. | H3: reset to X min = X dk'ya düşürülür, sıfırlanmaz
A4: Glyphs_TR.lua | B4: 163 | C4: Mekanik / anlam hatası | D4: Yüksek | E4: Innervate now grants the caster {1}% of <his/her> base mana pool over {2} sec in addition to the normal effects of Innervate. | F4: Innervate artık Innervate'in normal etkilerine ek olarak büyücüye {2} sn boyunca temel mana havuzunun %{1}'ini verir. | G4: Innervate artık Innervate'in normal etkilerine ek olarak büyüyü yapana {2} sn boyunca temel mana havuzunun %{1}'ini verir. | H4: caster = büyüyü yapan (büyücü Mage gibi okunur)
A5: Glyphs_TR.lua | B5: 273 | C5: Mekanik / anlam hatası | D5: Yüksek | E5: Your Blood Strike causes an additional {1}% damage to snared targets. | F5: Blood Strike'ınız köklenmiş hedeflere ek olarak %{1} hasar verir. | G5: Blood Strike'ın yavaşlatılmış hedeflere ek olarak %{1} hasar verir. | H5: snared = yavaşlatılmış, köklenmiş değil
A6: Spells_TR.lua | B6: 38 | C6: Mekanik / anlam hatası | D6: Yüksek | E6: A word of dark binding that inflicts {1} to {2} Shadow damage to the target. If the target is not killed by Shadow Word: Death, the caster takes damage equal to the damage inflicted upon the target. | F6: Hedefe {1} ila {2} Gölge hasarı veren karanlık bir bağlama sözü. Hedef Shadow Word: Death ile öldürülmezse büyücü, hedefe verilen hasara eşit hasar alır. | G6: Hedefe {1} ila {2} Gölge hasarı veren karanlık bir bağlama sözü. Hedef Shadow Word: Death ile öldürülmezse büyüyü yapan, hedefe verilen hasara eşit hasar alır. | H6: yanlış özne: caster büyücü değil
A7: Spells_TR.lua | B7: 55 | C7: Mekanik / anlam hatası | D7: Yüksek | E7: Afflicts the target with a disease that causes {1} Shadow damage over {2} sec. {3}% of damage caused by the Devouring Plague heals the caster. This spell can only affect one target at a time. | F7: Hedefi, {2} sn boyunca {1} Gölge hasarı veren bir hastalıkla etkiler. Devouring Plague'in verdiği hasarın %{3} kadarı büyücüyü iyileştirir. Bu büyü aynı anda yalnızca bir hedefi etkileyebilir. | G7: Hedefi, {2} sn boyunca {1} Gölge hasarı veren bir hastalıkla etkiler. Devouring Plague'in verdiği hasarın %{3} kadarı büyüyü yapanı iyileştirir. Bu büyü aynı anda yalnızca bir hedefi etkileyebilir. | H7: yanlış özne: caster büyücü değil
A8: Spells_TR.lua | B8: 401 | C8: Terim tutarlılığı | D8: Yüksek | E8: Gives your Destruction spells a {1}% chance to daze the target for {2} sec. | F8: Destruction büyülerine hedefi {2} sn boyunca sersemletme şansını %{1} verir. | G8: Destruction büyülerine hedefi {2} sn boyunca afallatma şansını %{1} verir. | H8: Daze = afallatma (Stun ile karışıyordu).
A9: Spells_TR.lua | B9: 429 | C9: Mekanik / anlam hatası | D9: Yüksek | E9: Heals a friendly target and the caster for {1} to {2}. Low threat. | F9: Dost bir hedefi ve büyücüyü {1} ila {2} iyileştirir. Düşük tehdit. | G9: Dost bir hedefi ve büyüyü yapanı {1} ila {2} iyileştirir. Düşük tehdit. | H9: Binding Heal: yanlış özne (büyücü).
A10: Spells_TR.lua | B10: 451 | C10: Terim tutarlılığı | D10: Yüksek | E10: Hurls a holy shield at the enemy, dealing {1} to {2} Holy damage, Dazing them and then jumping to additional nearby enemies. Affects {3} total targets. Lasts {4} sec. | F10: Düşmana kutsal bir kalkan fırlatır; {1} ila {2} Kutsal hasar verir, onları sersemletir ve ardından yakındaki ek düşmanlara sıçrar. Toplam {3} hedefi etkiler. {4} sn sürer. | G10: Düşmana kutsal bir kalkan fırlatır; {1} ila {2} Kutsal hasar verir, onları afallatır ve ardından yakındaki ek düşmanlara sıçrar. Toplam {3} hedefi etkiler. {4} sn sürer. | H10: Daze = afallatma, sersemletme değil.
A11: Spells_TR.lua | B11: 470 | C11: Mekanik / anlam hatası | D11: Yüksek | E11: Incapacitates the target for up to {1} min. Must be stealthed. Only works on Humanoids, Beasts, Demons and Dragonkin that are not in combat. Any damage caused will revive the target. Only {2} target may be sapped at a time. | F11: Hedefi {1} dk'ya kadar etkisiz hale getirir. Gizlenmiş olmalısın. Yalnızca savaşta olmayan Humanoid, Beast, Demon ve Dragonkin üzerinde işe yarar. Verilen herhangi bir hasar hedefi canlandırır. Aynı anda yalnızca {2} hedef Sap'lanabilir. | G11: Hedefi {1} dk'ya kadar etkisiz hale getirir. Gizlenmiş olmalısın. Yalnızca savaşta olmayan Humanoid, Beast, Demon ve Dragonkin üzerinde işe yarar. Verilen herhangi bir hasar hedefi uyandırır. Aynı anda yalnızca {2} hedef Sap'lanabilir. | H11: Sap: canlandırır yerine uyandırır.
A12: Spells_TR.lua | B12: 471 | C12: Mekanik / anlam hatası | D12: Yüksek | E12: Incapacitates the target for up to {1} sec. Must be stealthed. Only works on Humanoids that are not in combat. Any damage caused will revive the target. Only {2} target may be sapped at a time. | F12: Hedefi {1} sn'ye kadar etkisiz hale getirir. Gizlenmiş olmalısın. Yalnızca savaşta olmayan Humanoid üzerinde işe yarar. Verilen herhangi bir hasar hedefi canlandırır. Aynı anda yalnızca {2} hedef Sap'lanabilir. | G12: Hedefi {1} sn'ye kadar etkisiz hale getirir. Gizlenmiş olmalısın. Yalnızca savaşta olmayan Humanoid üzerinde işe yarar. Verilen herhangi bir hasar hedefi uyandırır. Aynı anda yalnızca {2} hedef Sap'lanabilir. | H12: Sap: canlandırır yerine uyandırır.
A13: Spells_TR.lua | B13: 755 | C13: Mekanik / anlam hatası | D13: Yüksek | E13: Places a Hand on the party or raid member, transfering {1}% damage taken to the caster. Lasts {2} sec or until the caster has transfered {3}% of their maximum health. Players may only have one Hand on them per Paladin at any one time. | F13: Grup veya akın üyesine bir Hand yerleştirerek alınan hasarın %{1}'ini büyücüye aktarır. {2} sn boyunca veya büyücü azami canının %{3}'ünü aktarana kadar sürer. Oyuncuların üzerinde her Paladin başına aynı anda yalnızca bir Hand bulunabilir. | G13: Grup veya raid üyesine bir Hand yerleştirerek alınan hasarın %{1}'ini büyüyü yapana aktarır. {2} sn boyunca veya büyüyü yapan maksimum canının %{3}'ünü aktarana kadar sürer. Oyuncuların üzerinde her Paladin başına aynı anda yalnızca bir Hand bulunabilir. | H13: büyücü yanlış özne (büyüyü yapan), azami->maksimum
... A1086: Talents_Tmpl_TR.lua | B1086: 847 | C1086: Okunurluk / yazım | D1086: Düşük | E1086: Your Starfire spell gains an additional {1}% and your Wrath gains an additional {2}% of your bonus damage effects. | F1086: Starfire büyün bonus hasar etkilerinin ek %{1}'sini ve Wrath'ın ek %{2}'sını kazanır. | G1086: Starfire büyün bonus hasar etkilerinden ek olarak %{1}, Wrath ise ek olarak %{2} kazanır. | H1086: yazım: %{2}'sını hatalı
